[
  {
    "Pshift": "A0-XA",
    "Frequency": 21,
    "Probability": 0.23,
    "P(S|D)": 0.57,
    "P(S|D,C)": 0.57,
    "Change of Speaker (C)": true,
    "Directed Remark (D)": false
  },
  {
    "Pshift": "A0-X0",
    "Frequency": 16,
    "Probability": 0.17,
    "P(S|D)": 0.43,
    "P(S|D,C)": 0.43,
    "Change of Speaker (C)": true,
    "Directed Remark (D)": false
  },
  {
    "Pshift": "A0-XY",
    "Frequency": 0,
    "Probability": 0.0,
    "P(S|D)": 0.0,
    "P(S|D,C)": 0.0,
    "Change of Speaker (C)": true,
    "Directed Remark (D)": false
  },
  {
    "Pshift": "A0-AY",
    "Frequency": 0,
    "Probability": 0.0,
    "P(S|D)": 0.0,
    "P(S|D,C)": "",
    "Change of Speaker (C)": false,
    "Directed Remark (D)": false
  },
  {
    "Pshift": "AB-BA",
    "Frequency": 26,
    "Probability": 0.28,
    "P(S|D)": 0.46,
    "P(S|D,C)": 0.46,
    "Change of Speaker (C)": true,
    "Directed Remark (D)": true
  },
  {
    "Pshift": "AB-B0",
    "Frequency": 19,
    "Probability": 0.2,
    "P(S|D)": 0.34,
    "P(S|D,C)": 0.34,
    "Change of Speaker (C)": true,
    "Directed Remark (D)": true
  },
  {
    "Pshift": "AB-X0",
    "Frequency": 1,
    "Probability": 0.01,
    "P(S|D)": 0.02,
    "P(S|D,C)": 0.02,
    "Change of Speaker (C)": true,
    "Directed Remark (D)": true
  },
  {
    "Pshift": "AB-XA",
    "Frequency": 10,
    "Probability": 0.11,
    "P(S|D)": 0.18,
    "P(S|D,C)": 0.18,
    "Change of Speaker (C)": true,
    "Directed Remark (D)": true
  },
  {
    "Pshift": "AB-XB",
    "Frequency": 0,
    "Probability": 0.0,
    "P(S|D)": 0.0,
    "P(S|D,C)": 0.0,
    "Change of Speaker (C)": true,
    "Directed Remark (D)": true
  },
  {
    "Pshift": "AB-A0",
    "Frequency": 0,
    "Probability": 0.0,
    "P(S|D)": 0.0,
    "P(S|D,C)": "",
    "Change of Speaker (C)": false,
    "Directed Remark (D)": true
  },
  {
    "Pshift": "AB-BY",
    "Frequency": 0,
    "Probability": 0.0,
    "P(S|D)": 0.0,
    "P(S|D,C)": 0.0,
    "Change of Speaker (C)": true,
    "Directed Remark (D)": true
  },
  {
    "Pshift": "AB-XY",
    "Frequency": 0,
    "Probability": 0.0,
    "P(S|D)": 0.0,
    "P(S|D,C)": 0.0,
    "Change of Speaker (C)": true,
    "Directed Remark (D)": true
  },
  {
    "Pshift": "AB-AY",
    "Frequency": 0,
    "Probability": 0.0,
    "P(S|D)": 0.0,
    "P(S|D,C)": "",
    "Change of Speaker (C)": false,
    "Directed Remark (D)": true
  }
]